README.rst
setup.py
callfire/__init__.py
callfire/base.py
callfire/callfire_v2.py
python_callfire.egg-info/PKG-INFO
python_callfire.egg-info/SOURCES.txt
python_callfire.egg-info/dependency_links.txt
python_callfire.egg-info/requires.txt
python_callfire.egg-info/top_level.txt