Metadata-Version: 1.1
Name: python-callfire
Version: 0.10.0
Summary: CallFire API thin wrapper.
Home-page: https://github.com/iMedicare/python-callfire
Author: Alexander Shchapov
Author-email: sasha@imedicare.com
License: MIT
Platform: UNKNOWN
Classifier: Development Status :: 4 - Beta
Classifier: Intended Audience :: Developers
Classifier: License :: OSI Approved :: MIT License
Classifier: Programming Language :: Python
Classifier: Programming Language :: Python :: 2.7
Classifier: Programming Language :: Python :: 3.5
